crypt4ghfs/__init__.py
crypt4ghfs/__main__.py
crypt4ghfs/app.py
crypt4ghfs/c4gh_files.py
crypt4ghfs/entry.py
crypt4ghfs/operations.py
crypt4ghfs-1.2.dist-info/METADATA
crypt4ghfs-1.2.dist-info/WHEEL
crypt4ghfs-1.2.dist-info/entry_points.txt
crypt4ghfs-1.2.dist-info/top_level.txt
crypt4ghfs-1.2.dist-info/RECORD
